cxgparser/__init__.py
cxgparser/cxgparser.py
cxgparser/version.py
cxgparser/resources/data/eng/1.0/constructions.ffr
cxgparser/resources/data/eng/1.0/learner_examplar_1.0.json
cxgparser/resources/data/eng/1.1/constructions.ffr
cxgparser/resources/data/eng/1.1/learner_examplar_1.1.json
cxgparser-1.3.4.dist-info/licenses/LICENSE
cxgparser-1.3.4.dist-info/METADATA
cxgparser-1.3.4.dist-info/WHEEL
cxgparser-1.3.4.dist-info/entry_points.txt
cxgparser-1.3.4.dist-info/top_level.txt
cxgparser-1.3.4.dist-info/RECORD
