Metadata-Version: 2.4
Name: cxgparser
Version: 1.3.4
Summary: A CxG Induction Parser.
Author-email: Lvxiaowei Xu <xlxw@zju.edu.cn>, Yaowen Xu <yaoxu@zju.edu.cn>, Zhilin Gong <zhilingong@gmail.com>, Anpeng Wu <anpwu@zju.edu.cn>, Ming Cai <cm@zju.edu.cn>
Project-URL: Repository, https://github.com/CxGrammar/CxGParser
Classifier: Intended Audience :: Science/Research
Classifier: Programming Language :: Python :: 3
Classifier: Topic :: Scientific/Engineering :: Artificial Intelligence
Requires-Python: >=3.10
License-File: LICENSE
Requires-Dist: cxglearner>=1.3.3b0
Provides-Extra: torch
Requires-Dist: torch>=2.6.0; extra == "torch"
Dynamic: license-file
